{
  "id": "ktF1Rr8EBFY",
  "url": "https://images.unsplash.com/photo-1554585343-acd99e31977b?crop=entropy&cs=tinysrgb&fit=max&fm=jpg&ixid=M3w0Mjk4MnwwfDF8YWxsfHx8fHx8fHx8MTcwNjU1MzIzMnw&ixlib=rb-4.0.3&q=80&w=1080",
  "external_url": "https://unsplash.com/photos/an-island-in-the-middle-of-a-lake-ktF1Rr8EBFY",
  "content_text": "Beautiful view of Visovac Island, National park Krka, Croatia",
  "_meta": {
    "venue": {
      "name": "Unsplash",
      "url": "https://unsplash.com"
    },
    "camera": {
      "iso": 100,
      "shutter_speed": "1/40",
      "aperture": "4",
      "make": "Hasselblad",
      "model": "L1D-20c"
    }
  },
  "author": {
    "name": "hrvoje_photography",
    "url": "https://unsplash.com/@hrvoje_photography",
    "avatar": "https://images.unsplash.com/profile-1551482965186-c83a5a764252?ixlib=rb-4.0.3&crop=faces&fit=crop&w=32&h=32"
  },
  "tags": null
}
